argilla_v1/__init__.py
argilla_v1/__main__.py
argilla_v1/_constants.py
argilla_v1/_messages.py
argilla_v1/_version.py
argilla_v1/errors.py
argilla_v1/logging.py
argilla_v1/cli/__init__.py
argilla_v1/cli/app.py
argilla_v1/cli/callback.py
argilla_v1/cli/rich.py
argilla_v1/cli/typer_ext.py
argilla_v1/cli/datasets/__init__.py
argilla_v1/cli/datasets/__main__.py
argilla_v1/cli/datasets/delete.py
argilla_v1/cli/datasets/list.py
argilla_v1/cli/datasets/push.py
argilla_v1/cli/info/__init__.py
argilla_v1/cli/info/__main__.py
argilla_v1/cli/login/__init__.py
argilla_v1/cli/login/__main__.py
argilla_v1/cli/logout/__init__.py
argilla_v1/cli/logout/__main__.py
argilla_v1/cli/training/__init__.py
argilla_v1/cli/training/__main__.py
argilla_v1/cli/users/__init__.py
argilla_v1/cli/users/__main__.py
argilla_v1/cli/users/create.py
argilla_v1/cli/users/delete.py
argilla_v1/cli/users/list.py
argilla_v1/cli/whoami/__init__.py
argilla_v1/cli/whoami/__main__.py
argilla_v1/cli/workspaces/__init__.py
argilla_v1/cli/workspaces/__main__.py
argilla_v1/cli/workspaces/add_user.py
argilla_v1/cli/workspaces/create.py
argilla_v1/cli/workspaces/delete_user.py
argilla_v1/cli/workspaces/list.py
argilla_v1/cli/workspaces/utils.py
argilla_v1/client/__init__.py
argilla_v1/client/api.py
argilla_v1/client/client.py
argilla_v1/client/datasets.py
argilla_v1/client/enums.py
argilla_v1/client/login.py
argilla_v1/client/models.py
argilla_v1/client/singleton.py
argilla_v1/client/users.py
argilla_v1/client/utils.py
argilla_v1/client/workspaces.py
argilla_v1/client/apis/__init__.py
argilla_v1/client/apis/base.py
argilla_v1/client/apis/datasets.py
argilla_v1/client/apis/metrics.py
argilla_v1/client/apis/search.py
argilla_v1/client/apis/status.py
argilla_v1/client/feedback/__init__.py
argilla_v1/client/feedback/config.py
argilla_v1/client/feedback/constants.py
argilla_v1/client/feedback/mixins.py
argilla_v1/client/feedback/unification.py
argilla_v1/client/feedback/dataset/__init__.py
argilla_v1-1.29.1.dist-info/LICENSE
argilla_v1-1.29.1.dist-info/METADATA
argilla_v1-1.29.1.dist-info/WHEEL
argilla_v1-1.29.1.dist-info/entry_points.txt
argilla_v1-1.29.1.dist-info/top_level.txt
argilla_v1-1.29.1.dist-info/RECORD
