Metadata-Version: 2.1
Name: argilla-v1
Version: 1.29.1
Summary: Open-source tool for exploring, labeling, and monitoring data for NLP projects.
Author-email: argilla <contact@argilla.io>
Maintainer-email: argilla <contact@argilla.io>
License: Apache-2.0
Project-URL: homepage, https://www.argilla.io
Project-URL: documentation, https://docs.v1.argilla.io
Project-URL: repository, https://github.com/argilla-io/argilla
Keywords: data-science,natural-language-processing,text-labeling,data-annotation,artificial-intelligence,knowledged-graph,developers-tools,human-in-the-loop,mlops
Requires-Python: <3.13,>=3.8
License-File: LICENSE
Requires-Dist: httpx <=0.26,>=0.15
Requires-Dist: deprecated ~=1.2.0
Requires-Dist: packaging >=20.0
Requires-Dist: pandas >=1.0.0
Requires-Dist: pydantic >=1.10.7
Requires-Dist: wrapt <1.15,>=1.14
Requires-Dist: numpy <1.27.0
Requires-Dist: tqdm >=4.27.0
Requires-Dist: backoff
Requires-Dist: monotonic
Requires-Dist: rich !=13.1.0
Requires-Dist: typer <0.10.0,>=0.6.0
Provides-Extra: integrations
Requires-Dist: PyYAML <6.1.0,>=5.4.1 ; extra == 'integrations'
Requires-Dist: datasets !=2.3.2,>1.17.0 ; extra == 'integrations'
Requires-Dist: huggingface-hub <0.24,>=0.5.0 ; extra == 'integrations'
Requires-Dist: flair >=0.12.2 ; extra == 'integrations'
Requires-Dist: faiss-cpu ; extra == 'integrations'
Requires-Dist: flyingsquid ; extra == 'integrations'
Requires-Dist: pgmpy ; extra == 'integrations'
Requires-Dist: plotly >=4.1.0 ; extra == 'integrations'
Requires-Dist: snorkel >=0.9.7 ; extra == 'integrations'
Requires-Dist: spacy <3.7.0,>=3.5.0 ; extra == 'integrations'
Requires-Dist: spacy-transformers >=1.2.5 ; extra == 'integrations'
Requires-Dist: spacy-huggingface-hub >=0.0.10 ; extra == 'integrations'
Requires-Dist: transformers[torch] >=4.30.0 ; extra == 'integrations'
Requires-Dist: evaluate ; extra == 'integrations'
Requires-Dist: seqeval ; extra == 'integrations'
Requires-Dist: sentence-transformers ; extra == 'integrations'
Requires-Dist: setfit >=1.0.0 ; extra == 'integrations'
Requires-Dist: span-marker ; extra == 'integrations'
Requires-Dist: sentence-transformers <3.0.0,>=2.0.0 ; extra == 'integrations'
Requires-Dist: textdescriptives <3.0.0,>=2.7.0 ; extra == 'integrations'
Requires-Dist: openai <1.0.0,>=0.27.10 ; extra == 'integrations'
Requires-Dist: peft ; extra == 'integrations'
Requires-Dist: trl >=0.5.0 ; extra == 'integrations'
Requires-Dist: ipynbname ; extra == 'integrations'
Provides-Extra: listeners
Requires-Dist: schedule ~=1.1.0 ; extra == 'listeners'
Provides-Extra: server
Requires-Dist: argilla-server ~=1.29.0 ; extra == 'server'
Provides-Extra: server-postgresql
Requires-Dist: argilla-server[postgresql] ~=1.29.0 ; extra == 'server-postgresql'
Provides-Extra: tests
Requires-Dist: pytest ; extra == 'tests'
Requires-Dist: pytest-cov ; extra == 'tests'
Requires-Dist: pytest-mock ; extra == 'tests'
Requires-Dist: pytest-asyncio ; extra == 'tests'
Requires-Dist: pytest-env ; extra == 'tests'
Requires-Dist: factory-boy ~=3.2.1 ; extra == 'tests'
